setup.py
bmu/__init__.py
bmu/__main__.py
bmu/build.py
bmu/cli.py
bmu/config.py
bmu/constants.py
bmu/github.py
bmu/label.py
bmu/server.py
bmu/validate.py
bmu.egg-info/PKG-INFO
bmu.egg-info/SOURCES.txt
bmu.egg-info/dependency_links.txt
bmu.egg-info/requires.txt
bmu.egg-info/top_level.txt