Metadata-Version: 1.0
Name: bmu
Version: 0.0.1
Summary: GitHub/Buildbot integration service
Home-page: https://github.com/bmcorser/bmu
Author: @bmcorser
Author-email: bmcorser@gmail.com
License: UNKNOWN
Platform: UNKNOWN
